setup.cfg
setup.py
gabi_probability/Binomialdistribution.py
gabi_probability/Gaussiandistribution.py
gabi_probability/Generaldistribution.py
gabi_probability/__init__.py
gabi_probability.egg-info/PKG-INFO
gabi_probability.egg-info/SOURCES.txt
gabi_probability.egg-info/dependency_links.txt
gabi_probability.egg-info/not-zip-safe
gabi_probability.egg-info/top_level.txt