Metadata-Version: 1.0
Name: gabi-probability
Version: 1.0
Summary: Gaussian and Binomial distributions
Home-page: UNKNOWN
Author: Sparsh Garg
Author-email: sparsh.garg2019@outlook.com
License: UNKNOWN
Platform: UNKNOWN
